LICENSE.txt
MANIFEST.in
README.md
setup.cfg
setup.py
Converto.egg-info/PKG-INFO
Converto.egg-info/SOURCES.txt
Converto.egg-info/dependency_links.txt
Converto.egg-info/entry_points.txt
Converto.egg-info/requires.txt
Converto.egg-info/top_level.txt
converto/__init__.py
converto/command_line.py
converto/config.py
converto/converto.py
converto/file_finder.py
converto/configuration/configuration.json