Metadata-Version: 1.2
Name: Converto
Version: 1.1.0
Summary: A simple, configurable wrapper for FFmpeg
Home-page: https://github.com/erikmhauck/converto
Author: Erik Hauck
Author-email: UNKNOWN
License: MIT
Project-URL: Documentation, https://github.com/erikmhauck/converto
Project-URL: Source, https://github.com/erikmhauck/converto
Project-URL: Tracker, https://github.com/erikmhauck/converto/issues
Keywords: ffmpeg wrapper configurable tool
Platform: UNKNOWN
Classifier: Development Status :: 5 - Production/Stable
Classifier: Intended Audience :: End Users/Desktop
Classifier: Topic :: Multimedia
Classifier: License :: OSI Approved :: MIT License
Classifier: Programming Language :: Python :: 2.7
Classifier: Programming Language :: Python :: 3
Classifier: Programming Language :: Python :: 3.2
Classifier: Programming Language :: Python :: 3.3
Classifier: Programming Language :: Python :: 3.4
Classifier: Programming Language :: Python :: 3.5
Classifier: Programming Language :: Python :: 3.6
Requires-Python: >=2.7, <4
